odoo/addons/product_variant_sale_order_route/README.rst
odoo/addons/product_variant_sale_order_route/__init__.py
odoo/addons/product_variant_sale_order_route/__manifest__.py
odoo/addons/product_variant_sale_order_route/i18n/product_variant_sale_order_route.pot
odoo/addons/product_variant_sale_order_route/models/__init__.py
odoo/addons/product_variant_sale_order_route/models/product.py
odoo/addons/product_variant_sale_order_route/models/sale_order_line.py
odoo/addons/product_variant_sale_order_route/readme/CONTRIBUTORS.rst
odoo/addons/product_variant_sale_order_route/readme/DESCRIPTION.rst
odoo/addons/product_variant_sale_order_route/static/description/icon.png
odoo/addons/product_variant_sale_order_route/static/description/index.html
odoo/addons/product_variant_sale_order_route/tests/__init__.py
odoo/addons/product_variant_sale_order_route/tests/test_sale_order.py
odoo/addons/product_variant_sale_order_route/views/product_view.xml
odoo11_addon_product_variant_sale_order_route-11.0.1.0.0.99.dev3.dist-info/METADATA
odoo11_addon_product_variant_sale_order_route-11.0.1.0.0.99.dev3.dist-info/WHEEL
odoo11_addon_product_variant_sale_order_route-11.0.1.0.0.99.dev3.dist-info/top_level.txt
odoo11_addon_product_variant_sale_order_route-11.0.1.0.0.99.dev3.dist-info/RECORD
